[
    {
        "question": "What does the Content-Type HTTP response header do?",
        "options": [
            "Not assigned",
            "It contains information about the software used by the origin server",
            "It specifies response MIME media types which are acceptable",
            "It indicates whether the response has been compressed or not",
            "It specifies the MIME media type of the associated resource"
        ],
        "correctAnswer": 4,
        "verified": 1
    },
    {
        "question": "What are the main technologies of Web 1.0?",
        "options": [
            "HTTP, RDF, MIME, URL",
            "HTTP, HTML, AJAX, URL",
            "HTTP, SPARQL, MIME, URL",
            "HTTP, HTML, MIME, URL",
            "Not assigned"
        ],
        "correctAnswer": 3,
        "verified": 1
    },
    {
        "question": "What is an RDF triple?",
        "options": [
            "It is a relationship among rows belonging to three different tables",
            "It is a mechanism to encode information in a more secure way",
            "It is the way to connect HTTP, AJAX, and REST",
            "It is a statement of the form subject, predicate, object",
            "Not assigned"
        ],
        "correctAnswer": 3,
        "verified": 1
    },
    {
        "question": "What is an Element Node in XML?",
        "options": [
            "It represents the additional properties of a Node",
            "It is a fragment of unstructured information",
            "It is a logical grouping of the information represented by its descendant",
            "It is a fragment of textual content ignored in the processing",
            "Not assigned"
        ],
        "correctAnswer": 2,
        "verified": 1
    },
    {
        "question": "How does HTTP basic authentication work?",
        "options": [
            "Username and password are concatenated with a colon and then Base64 encoded in the WWW-Authenticate header",
            "Username and password are Base64 encoded and then concatenated with a colon in the WWW-Authenticate header",
            "Username and password are concatenated with a colon and then Base64 encoded in the Authorization header",
            "Username and password are Base64 encoded and then concatenated with a colon in the Authorization header",
            "Not assigned"
        ],
        "correctAnswer": 2,
        "verified": 1
    },
    {
        "question": "What is a descriptive markup language?",
        "options": [
            "It defines the type or class of the content to indicate its intended use",
            "It provides the means for extending the vocabulary of the language",
            "Not assigned",
            "It refers to entities external to the document",
            "It contains commands to format and layout the content"
        ],
        "correctAnswer": 0,
        "verified": 1
    },
    {
        "question": "What is the purpose of the application logic layer?",
        "options": [
            "To manage the persistent storage of the data",
            "To define and control the flow of operations in the application",
            "To manage the interaction with the user",
            "Not assigned",
            "To define the format and visualisation of information"
        ],
        "correctAnswer": 1,
        "verified": 1
    },
    {
        "question": "What is a single-tier architecture?",
        "options": [
            "A Web server/database server architecture",
            "A fat client/database server architecture",
            "Not assigned",
            "A thin client/Web server architecture",
            "A dumb terminal/mainframe architecture"
        ],
        "correctAnswer": 4,
        "verified": 1
    },
    {
        "question": "How does the JSP technology work?",
        "options": [
            "Not assigned",
            "A pre-processor translates a JSP into a servlet and then the servlet processes the request",
            "The JSP page directly returns the response to the client, after processing the request",
            "The JSP is executed by an interpreter, like PHP, and processes the request",
            "The JSP page forwards the request to a servlet which processes it"
        ],
        "correctAnswer": 1,
        "verified": 1
    },
    {
        "question": "Which elements are selected by the following CSS selector? <br>p a {<br>...<br>}",
        "options": [
            "Any &lt;a&gt; element inside a &lt;p&gt; element",
            "Any &lt;p&gt; element that has at least one &lt;a&gt; element as direct child",
            "Only &lt;a&gt; elements that are direct children of a &lt;p&gt; element",
            "Any &lt;p&gt; element which has an &lt;a&gt; element inside",
            "Not assigned"
        ],
        "correctAnswer": 0,
        "verified": 1
    },
    {
        "question": "What is a jQuery object?",
        "options": [
            "It is an object similar to the DOM object in JavaScript.",
            "It is a set of zero or more DOM elements.",
            "Not assigned",
            "It is a single DOM element in jQuery language.",
            "It is an object similar to the Window object in JavaScript."
        ],
        "correctAnswer": 1,
        "verified": 1
    },
    {
        "question": "What is the dark Web?",
        "options": [
            "It is the Web ensuring anonymity",
            "It is the Web of static pages",
            "It is the not indexable Web",
            "It is the Web originated from databases",
            "Not assigned"
        ],
        "correctAnswer": 0,
        "verified": 1
    },
    {
        "question": "What is the deep Web?",
        "options": [
            "It is the Web ensuring anonymity",
            "It is the Web of static pages",
            "It is the not indexable Web",
            "It is the Web originated from databases",
            "Not assigned"
        ],
        "correctAnswer": 2,
        "verified": 1
    },
    {
        "question": "What is the purpose of the MIME multipart media type?",
        "options": [
            "To split a single body into multiple parts for more efficient transmission",
            "To multiplex multiple requests and responses into a single stream of data",
            "To describe content where one or more sets of data are combined into a single body",
            "To describe each single part constituting an URI",
            "Not assigned"
        ],
        "correctAnswer": 2,
        "verified": 1
    },
    {
        "question": "How can you attach an external CSS to your HTML document?",
        "options": [
            "Insert the following element in the &lt;heading&gt; element &lt;link rel=\"stylesheet\" type=\"text/css\" src=\"mystyle.css\"&gt;",
            "Insert the following element at the beginning of the &lt;body&gt; element &lt;link rel=\"stylesheet\" type=\"text/css\" href=\"mystyle.css\"&gt;",
            "Insert the following element in the &lt;head&gt; element &lt;link rel=\"stylesheet\" type=\"text/css\" href=\"mystyle.css\"&gt;",
            "Insert the following element in the &lt;head&gt; element &lt;link rel=\"stylesheet\" type=\"text/css\" src=\"mystyle.css\"&gt;",
            "Not assigned"
        ],
        "correctAnswer": 2,
        "verified": 1
    },
    {
        "question": "What is the percent encoding?",
        "options": [
            "A compression encoding for textual resources",
            "The UTF-8 encoding of characters",
            "Not assigned",
            "An escaping of reserved and not plain ASCII characters in URI, based on % plus hexadecimal representation of octets",
            "A way to represent binary data in textual HTTP requests"
        ],
        "correctAnswer": 3,
        "verified": 1
    },
    {
        "question": "What are the issues of extended ASCII?",
        "options": [
            "Compatibility issues among different countries",
            "Waste of space issues due to many unused characters",
            "Not assigned",
            "Compatibility issues with the previous 7 bits version of ASCII",
            "Compatibility issues with the previous 32 bits version of Unicode"
        ],
        "correctAnswer": 0,
        "verified": 1
    },
    {
        "question": "What is Maven?",
        "options": [
            "It is a site and documentation tool",
            "Not assigned",
            "It is a tool for managing the build process of Java software projects",
            "It is a Web server for running Java servlets",
            "It is a tool for managing the cooperative development of source code"
        ],
        "correctAnswer": 2,
        "verified": 1
    },
    {
        "question": "What does the following element represent? &lt;a src=&quot;http://www.example.com/index.html#bottom&quot;&gt;",
        "options": [
            "None of the other answers",
            "A link to a specific page fragment",
            "Not assigned",
            "A link to an element on the same page",
            "A link to a specific web page"
        ],
        "correctAnswer": 0,
        "verified": 1
    },
    {
        "question": "What is the purpose of the <u>service</u> method in a Java servlet?",
        "options": [
            "Not assigned",
            "It allows the servlet to cleanup resources",
            "It allows the servlet to send a request",
            "It allows the servlet to respond to a request",
            "It allows the servlet to accept a response"
        ],
        "correctAnswer": 3,
        "verified": 1
    },
    {
        "question": "How can you associate an image with its caption with HTML5?",
        "options": [
            "Use the &lt;figure&gt;, &lt;img&gt; and &lt;p&gt; elements",
            "Not assigned",
            "Use the &lt;figure&gt;, &lt;img&gt; and &lt;figcaption&gt; elements",
            "You need only the &lt;img&gt; and &lt;figcaption&gt; elements",
            "You need only the &lt;figure&gt; and &lt;figcaption&gt; elements"
        ],
        "correctAnswer": 2,
        "verified": 1
    },
    {
        "question": "What is AJAX?",
        "options": [
            "It is a server-side technology to programmatically issue HTTP requests",
            "It is a technology to define the structure of a Web page",
            "It is a client-side technology to programmatically issue HTTP requests",
            "It is a technology to define the presentation of a Web page",
            "Not assigned"
        ],
        "correctAnswer": 2,
        "verified": 1
    },
    {
        "question": "Who did invent the memex?",
        "options": [
            "Ted Nelson",
            "Douglas Engelbart",
            "Tim Berners-Lee",
            "Vannevar Bush",
            "Not assigned"
        ],
        "correctAnswer": 3,
        "verified": 1
    },
    {
        "question": "What does the HTTP PUT method do?",
        "options": [
            "It request the server to accept the entity enclosed in the request under the resource identified by a URI",
            "Not assigned",
            "It retrieves the resource identified by a URI",
            "Represents a request for information about the resource identified by a URI",
            "It requests that the resource identified by a URI is updated by the enclosed entity"
        ],
        "correctAnswer": 4,
        "verified": 1
    },
    {
        "question": "What is a browser?",
        "options": [
            "A client for sending email to an email server",
            "A server which provides Web pages",
            "A software which allows for displaying Web pages",
            "Not assigned",
            "Part of the HTTP protocol"
        ],
        "correctAnswer": 2,
        "verified": 1
    },
    {
        "question": "What is an URI?",
        "options": [
            "It is a specific and concrete identification mechanism",
            "It is a standard to support the encoding of resources",
            "Not assigned",
            "It is the format of a resource",
            "It is a sequence of character which uniquely identifies a resource"
        ],
        "correctAnswer": 4,
        "verified": 1
    },
    {
        "question": "What is the canvas element?",
        "options": [
            "Not assigned",
            "It is a CSS3 media query element for responsive applications",
            "It is a CSS3 container for floating objects",
            "It is an HTML5 element which allows for drawing graphics by using JavaScript",
            "It is an HTML5 element which allows for drawing graphics by using SVG"
        ],
        "correctAnswer": 3,
        "verified": 1
    },
    {
        "question": "What is a Java servlet?",
        "options": [
            "It is a client-side technology which loads dynamic Web content",
            "It is a client-side technology which generates dynamic Web content",
            "It is a server-side technology which cannot provide static Web content",
            "Not assigned",
            "It is a server-side technology which generates dynamic Web content"
        ],
        "correctAnswer": 4,
        "verified": 1
    },
    {
        "question": "What does the HTTP POST method do?",
        "options": [
            "It requests that the resource identified by a URI is updated by the enclosed entity",
            "Represents a request for information about the resource identified by a URI",
            "It request the server to accept the entity enclosed in the request under the resource identified by a URI",
            "It retrieves the resource identified by a URI",
            "Not assigned"
        ],
        "correctAnswer": 2,
        "verified": 1
    },
    {
        "question": "What is a cookie?",
        "options": [
            "It contains information about the software used by the origin server",
            "Not assigned",
            "It is a way for the client to store state information into the server",
            "It is a way of implementing a caching mechanism for HTTP",
            "It is a way for the server to store state information into the client"
        ],
        "correctAnswer": 4,
        "verified": 1
    },
    {
        "question": "What is MIME?",
        "options": [
            "A way to authenticating resources on the Web",
            "A way to encode Unicode characters",
            "An encoding for escaping reserved and not plain ASCII characters in URI",
            "An Internet standard to support the encoding of information for email and the Web",
            "Not assigned"
        ],
        "correctAnswer": 3,
        "verified": 1
    },
    {
        "question": "What is a Text Node in XML?",
        "options": [
            "It is a logical grouping of the information represented by its descendant",
            "It represents the additional properties of an element",
            "Not assigned",
            "It is a fragment of textual content ignored in the processing",
            "It is a fragment of unstructured information"
        ],
        "correctAnswer": 4,
        "verified": 1
    },
    {
        "question": "Which of the following is an HTML5 page layout element?",
        "options": [
            "&lt;title&gt;",
            "&lt;head&gt;",
            "Not assigned",
            "&lt;nav&gt;",
            "&lt;content&gt;"
        ],
        "correctAnswer": 3,
        "verified": 1
    },
    {
        "question": "What is a Web Application Architecture?",
        "options": [
            "It is a case of two-tiers architecture",
            "It is a case of single-tier architecture",
            "It is a case of three-tiers architecture",
            "It is a fat client/thin server architecture",
            "Not assigned"
        ],
        "correctAnswer": 2,
        "verified": 1
    },
    {
        "question": "How do you specify a paragraph box with top padding of 10 px, bottom padding of 20 px, left padding of 1 px, and right padding of 5px?",
        "options": [
            "p { padding: 10px 20px 1px 5px; }",
            "p { padding: 10px 1px 20px 5px; }",
            "Not assigned",
            "p { padding: 5px 20px 1px 10px; }",
            "p { padding: 10px 5px 20px 1px; }"
        ],
        "correctAnswer": 4,
        "verified": 1
    },
    {
        "question": "What is the purpose of the &lt;title&gt; element?",
        "options": [
            "It does not display its content since it is only used by search engines",
            "It displays the title of the page on the url bar",
            "Not assigned",
            "It displays the title of the page on the body",
            "It displays the title of the page on the window tab"
        ],
        "correctAnswer": 4,
        "verified": 1
    },
    {
        "question": "What is the correct jQuery code to set the color of all p elements to red?",
        "options": [
            "$(\"p\").attr(\"color\",\"red\");",
            "$(\"p\").css(\"color\",\"red\");",
            "$(\"p\").style(\"color\",\"red\");",
            "$(\"p\").style(\"text-color\",\"red\");",
            "Not assigned"
        ],
        "correctAnswer": 1,
        "verified": 1
    },
    {
        "question": "What is a Web service?",
        "options": [
            "A Web service is an AJAX-based application which allows for the mash-up of different APIs into a rich client interface",
            "Not assigned",
            "A Web service is a Web container, like Apache Tomcat, to run Web applications",
            "A Web service is a software system designed to support interoperable machine-to-machine interaction over a network, exploiting standard Web technologies",
            "A Web service is a design pattern for Web application, allowing for distributed transaction processing"
        ],
        "correctAnswer": 3,
        "verified": 1
    },
    {
        "question": "What did Vannevar Bush proposed?",
        "options": [
            "The Xanadu project",
            "The term hypertext",
            "Not assigned",
            "The Memex",
            "The first browser"
        ],
        "correctAnswer": 3,
        "verified": 1
    },
    {
        "question": "What is the main feature of the DOM API?",
        "options": [
            "It creates an in-memory representation of XML tree",
            "It provides an unidirectional access (forward only) to the XML tree",
            "It facilitates the parsing of huge XML files",
            "It provides a bi-directional access to the XML tree",
            "It is a streaming push API"
        ],
        "correctAnswer": 0,
        "verified": 1
    },
    {
        "question": "Which of the following sentences is correct?",
        "options": [
            "Only positive values are admissible for the margin property",
            "Top and bottom margins do not affect inline text elements",
            "Not assigned",
            "The value of the margin property is inherited by child elements",
            "The top and bottom margins of neighboring elements do not collapse"
        ],
        "correctAnswer": 1,
        "verified": 1
    },
    {
        "question": "Which of the following is a mouse event?",
        "options": [
            "Not assigned",
            "mouseonclick",
            "mousemove",
            "mousescroll",
            "rightclick"
        ],
        "correctAnswer": 2,
        "verified": 1
    },
    {
        "question": "What does the Content-Encoding HTTP response header do?",
        "options": [
            "It specifies response MIME media types which are acceptable",
            "It indicates how the response has been compressed",
            "It specifies the MIME media type of the associated resource",
            "It contains information about the software used by the origin server",
            "Not assigned"
        ],
        "correctAnswer": 1,
        "verified": 1
    },
    {
        "question": "What is server push?",
        "options": [
            "It is a bidirectional communication modality enabled via Websockets",
            "It is an HTTP/2 feature used by the clients to proactively ask for contents to the server",
            "It is an HTTP/2 feature used by the server to proactively send contents to the client",
            "It is the cause of the HTTP HOL blocking issue",
            "Not assigned"
        ],
        "correctAnswer": 2,
        "verified": 1
    },
    {
        "question": "What is Git?",
        "options": [
            "It is a tool for managing the build process of Java software projects",
            "Not assigned",
            "It is a tool for managing the cooperative development of source code",
            "It is a continuous integration framework",
            "It is a site and documentation tool"
        ],
        "correctAnswer": 2,
        "verified": 1
    },
    {
        "question": "What is a procedural mark-up language?",
        "options": [
            "It defines the type or class of the content, e.g. to indicate its intended use",
            "It consists of commands indicating how text should be formatted",
            "It deals with the actual laying out of contents on a page",
            "Not assigned",
            "It provides the means for extending the vocabulary of descriptive markup languages"
        ],
        "correctAnswer": 1,
        "verified": 1
    },
    {
        "question": "Which of the following is an HTML block element?",
        "options": [
            "&lt;img&gt;",
            "&lt;a&gt;",
            "&lt;b&gt;",
            "Not assigned",
            "&lt;li&gt;"
        ],
        "correctAnswer": 4,
        "verified": 1
    },
    {
        "question": "What is the purpose of the HTTP DELETE request method in REST?",
        "options": [
            "To read a resource",
            "To delete a resource",
            "To update a resource",
            "To create a resource",
            "Not assigned"
        ],
        "correctAnswer": 1,
        "verified": 1
    },
    {
        "question": "What is a recursive relationship in the ER model?",
        "options": [
            "It is a relationships where at least one entity participates more than once",
            "It is a relationship between an entity and itself",
            "It is a relationships where only one entity participates more than once",
            "It is a relationship nested with another relationship"
        ],
        "correctAnswer": 1,
        "verified": 0
    },
    {
        "question": "What is HTTP/2 server push?",
        "options": [
            "The server can push additional resources to the client without the client having to request for each of them",
            "The server can store session information in a dedicated storage on the client",
            "The client can push multiple requests to the server in parallel without waiting for the responses",
            "The client can store multiple contents in a server-side cache"
        ],
        "correctAnswer": 0,
        "verified": 1
    },
    {
        "question": "The JavaScript ForEach() method:",
        "options": [
            "Iterates through an array of objects, providing access to the object properties.",
            "Iterates through an array, invoking a function you specify for each element.",
            "Iterates through an object, invoking a function you specify for each property.",
            "It is a simple iterator on the array elements"
        ],
        "correctAnswer": 1,
        "verified": 1
    },
    {
        "question": "What is a one-to-one relationship in the ER model?",
        "options": [
            "A relationship where each instance of an entity is associated with one or more instances of another entity",
            "A relationship where each instance of an entity is associated with one and only one instance of another entity",
            "A relationship where one or more instances of an entity are associated with one or more instances of another entity",
            "A recursive relationship where only one entity takes part"
        ],
        "correctAnswer": 1,
        "verified": 0
    },
    {
        "question": "What is an external identiﬁer in the ER model?",
        "options": [
            "It is an identiﬁer constituted only by attributes of other entities in relationship with a given entity",
            "It is an identiﬁer constituted only by attributes of a single entity",
            "It is an identiﬁer which is managed outside from the database",
            "It is an identiﬁer constituted by attributes of a given entity and also those of other entities in relationship with that entity"
        ],
        "correctAnswer": 0,
        "verified": 1
    },
    {
        "question": "Suppose you need to create a foreign key towards the following table <br>CREATE TABLE Example (<br> i INT,<br> j INT,<br> PRIMARY KEY (i, j)<br> );<br> Which statement is correct?",
        "options": [
            "CREATE TABLE Example2 (<br> a INT PRIMARY KEY,<br> i INT,<br> j INT,<br> FOREIGN KEY (i, j) REFERENCES Example(i, j)<br> );",
            "CREATE TABLE Example2 (<br> a INT PRIMARY KEY,<br> i INT REFERENCES Example(i),<br> j INT REFERENCES Example(j)<br> );",
            "CREATE TABLE Example2 (<br> a INT PRIMARY KEY,<br> i INT,<br> j INT,<br> FOREIGN KEY (i) REFERENCES Example(i),<br> FOREIGN KEY (j) REFERENCES Example(j)<br> );",
            "CREATE TABLE Example2 (<br> a INT PRIMARY KEY,<br> i, j INT REFERENCES Example(i, j)<br> );"
        ],
        "correctAnswer": 0,
        "verified": 0
    },
    {
        "question": "What does IDEMPOTENT HTTP method mean?",
        "options": [
            "It is a method which prevents the automatic repetition of the same request",
            "It is a method whose multiple invocations produce different effects",
            "It is a method which cannot be cached",
            "It is a method whose multiple invocations produce the same effect as a single one"
        ],
        "correctAnswer": 3,
        "verified": 1
    },
    {
        "question": "What is the typical implementation of the MVC pattern using Java technologies?",
        "options": [
            "JavaBeans are the model, servlets are the View, and JSP are the Controller",
            "Servlets are the model, JSP are the View, and JavaBeans are the Controller",
            "JSP are the model, JavaBeans are the View, and servlets are the Controller",
            "JavaBeans are the model, JSP are the View, and servlets are the Controller"
        ],
        "correctAnswer": 3,
        "verified": 1
    },
    {
        "question": "What is the hypertext design?",
        "options": [
            "It specifies the site views to be constructed on top of the data schema to realize the content publishing and manipulation services",
            "It specifies the appearance of the Web site by means of physical structures, dependent on the DBMS structure",
            "It is a representation of the mini-world by means of the physical schema and mockups, according to the customer’s requirements",
            "It is a representation of the mini-world by means of a high-level site view models, integrating all the relevant concepts and independent from the DBMS"
        ],
        "correctAnswer": 0,
        "verified": 1
    },
    {
        "question": "Suppose you have the following table <br>CREATE TABLE Example (<br> taskID INT,<br> description VAR-CHAR(64),<br> supertask INT,<br> PRIMARY KEY (taskID),<br> FOREIGN KEY (supertask) REFERENCES Example(taskID));<br> containing the following<br> dataTaskID Description Supertask<br>10 Task 1011 Task 11 4512 Task 12 3713 Task 13 2929 Task 29 37194 Task 194 29<br> and that you need to determine how many sub-tasks there are for each task. Which statement is correct?",
        "options": [
            "SELECT supertask,<br> COUNT(*) AS subtasks FROM Example<br> GROUP BY supertask;",
            "SELECT taskID,<br> COUNT(*) AS subtasks FROM Example<br> GROUP BY supertask;",
            "SELECT supertask,<br> COUNT(*) AS subtasks FROM Example<br> WHERE supertask IS NOT NULL<br> GROUP BY supertask;",
            "SELECT taskID,<br> COUNT(*) AS subtasks FROM Example<br> GROUP BY taskID;"
        ],
        "correctAnswer": 2,
        "verified": 1
    },
    {
        "question": "What is a relationship in the ER model?",
        "options": [
            "It is a class of objects of the real world which exist autonomously",
            "It is a local property of some objects relevant for the application",
            "It is a container of connections",
            "It is an association among two or more entities"
        ],
        "correctAnswer": 3,
        "verified": 0
    },
    {
        "question": "What is the effect of position: float?",
        "options": [
            "It removes an element from the normal flow and places it in the first available slot",
            "It moves an element as far as possible to the left or right",
            "It removes an element from the normal flow and it is used to place elements side by side",
            "Nothing, the syntax is not correct"
        ],
        "correctAnswer": 3,
        "verified": 1
    },
    {
        "question": "What is the jQuery method which corresponds to the JavaScript load event on the Window object?",
        "options": [
            "ready()",
            "load()",
            "documentLoad()",
            "documentReady()"
        ],
        "correctAnswer": 0,
        "verified": 1
    },
    {
        "question": "How are different parts separated in a MIME multipart content?",
        "options": [
            "There is a blank line separating each part",
            "There is an arbitrary sequence of characters, not appearing in any part, used a boundary",
            "There is a random boundary which is the same for each part and it is prefixed by –",
            "There is a random boundary which changes for each part and it is prefixed by -"
        ],
        "correctAnswer": 1,
        "verified": 1
    },
    {
        "question": "What data type is most appropriate for representing a telephone number?",
        "options": [
            "INT",
            "VARCHAR(11)",
            "BIGINT",
            "CHAR(11)"
        ],
        "correctAnswer": 1,
        "verified": 1
    },
    {
        "question": "What is a foreign key in the relational model?",
        "options": [
            "It is a set of one or more attributes of a relation which refer to a primary key of another table in order to link tuples",
            "It is the primary key of the table when using foreign data wrappers",
            "It is a single attribute of a relation whose value is unique for each tuple of the relation",
            "It is a set of one or more attributes of a relation whose values are unique for each tuple of the relation"
        ],
        "correctAnswer": 0,
        "verified": 0
    },
    {
        "question": "What data type is most appropriate for representing a ZIP code?",
        "options": [
            "CHAR(5)",
            "SMALLINT",
            "INT",
            "VARCHAR(5)"
        ],
        "correctAnswer": 3,
        "verified": 1
    },
    {
        "question": "Which of the following is <u>NOT</u> JavaScript primitive type?",
        "options": [
            "Byte",
            "Boolean",
            "Null",
            "String"
        ],
        "correctAnswer": 0,
        "verified": 1
    },
    {
        "question": "Which of the following are JavaScript primitive type?",
        "options": [
            "Byte",
            "Boolean",
            "Null",
            "String"
        ],
        "correctAnswer": [1, 2, 3],
        "verified": 1
    },
    {
        "question": "What does it mean that SQL is a declarative language?",
        "options": [
            "It means that you can declare variables",
            "It means that you express what you need and the actual sequence of operations needed to produce it",
            "It means that you can express functional dependencies among instructions",
            "It means that you express what you need but not the actual sequence of operations needed to produce it"
        ],
        "correctAnswer": 3,
        "verified": 0
    },
    {
        "question": "Suppose you need to create a table with a primary key constituted by a pair of columns. Which statement is correct?",
        "options": [
            "CREATE TABLE Example ( i INT, j INT, PRIMARY KEY (i), PRIMARY KEY (j) );",
            "CREATE TABLE Example ( i INT PRIMARY KEY, j INT PRIMARY KEY );",
            "CREATE TABLE Example ( i INT, j INT, PRIMARY KEY (i, j) );",
            "CREATE TABLE Example ( i, j INT PRIMARY KEY );"
        ],
        "correctAnswer": 2,
        "verified": 0
    },
    {
        "question": "What is an entity in the ER model?",
        "options": [
            "It is a connection among two or more objects",
            "It is a class of objects of the real world which exist autonomously",
            "It is a container of records",
            "It is a local property of some objects relevant for the application"
        ],
        "correctAnswer": 1,
        "verified": 0
    },
    {
        "question": "What is a primary key in the relational model?",
        "options": [
            "It is a set of one or more attributes of a relation used to link rows to rows of another relation",
            "It is the most important attribute of a relation",
            "It is a set of one or more attributes of a relation whose values are unique for each tuple of the relation",
            "It is a single attribute of a relation whose value is unique for each tuple of the relation"
        ],
        "correctAnswer": 2,
        "verified": 0
    },
    {
        "question": "Suppose you have the following table<br> CREATE TABLE Example (<br> taskID INT,<br> description VAR-CHAR(64),<br> supertask INT,<br> PRIMARY KEY (taskID),<br> FOREIGN KEY (supertask)<br> REFERENCES Example(taskID));<br> containing the following data<br>TaskID Description Supertask<br>10 Task 1011 Task 11 4512 Task 12 3713 Task 13 2929 Task 29 37194 Task 194 29<br> and that you need to determine which are the root tasks. Which statement is correct?",
        "options": [
            "SELECT taskID FROM Example WHERE supertask IS NULL;",
            "SELECT taskID FROM Example WHERE supertask = NULL;",
            "SELECT taskID FROM Example WHERE supertask IS NOT NULL;",
            "SELECT taskID FROM Example WHERE supertask <> NULL;"
        ],
        "correctAnswer": 0,
        "verified": 0
    },
    {
        "question": "What is the WebML Hypertext Model?",
        "options": [
            "It is a methodology for hypertext design which follows the style of both, Entity-Relationship and UML offering a proprietary notation and a graphical representation",
            "It is a methodology for hypertext design which is based on a UML profile for the hypermedia domain",
            "It is a methodology for hypertext design which is based on a precise OMT model that characteizes the different notation elements and the relationships between them",
            "It is a methodology for hypertext design which uses the user interaction diagrams (UIDs) to graphically model the interaction between the users and the system"
        ],
        "correctAnswer": 0,
        "verified": 0
    },
    {
        "question": "Which of the following are popular techniques used for requirements validation?",
        "options": [
            "Prototyping",
            "Checklist",
            "Interview",
            "Formal description"
        ],
        "correctAnswer": 3,
        "verified": 0
    },
    {
        "question": "How is an entity represented in the ER model?",
        "options": [
            "By means of a rhombus with a unique name inside",
            "By means of a rectangle with a unique name inside",
            "By means of a rectangle with a name inside",
            "By means of a rhombus with a name inside"
        ],
        "correctAnswer": 1,
        "verified": 0
    },
    {
        "question": "What is a cardinality constraint in the ER model?",
        "options": [
            "A bound to the number of instances of a relationship to which each instance of an entity can participate",
            "A bound to the number of entities which can participate to a relationship",
            "A bound to the number of instances of an entity which have the same value for an attribute",
            "A bound to the number of values which can be associated to an attribute"
        ],
        "correctAnswer": 0,
        "verified": 0
    },
    {
        "question": "What does SAFE HTTP method mean?",
        "options": [
            "It is a method with side effects, i.e. read-only",
            "It is a method without side effects, i.e. read-write",
            "It is a method with side effects, i.e. read-write",
            "It is a method without side effects, i.e. read-only"
        ],
        "correctAnswer": 3,
        "verified": 1
    },
    {
        "question": "A RDF predicate can be",
        "options": [
            "A function call",
            "An HTTP request method",
            "An URI",
            "A literal"
        ],
        "correctAnswer": 2,
        "verified": 1
    },
    {
        "question": "JavaScript arrays:",
        "options": [
            "Can have elements of any type, the type and the array length should be declared.",
            "Can have elements of any type, but different elements of the same array can not be of different types.",
            "Can have elements of any type, and different elements of the same array may be of different types.",
            "Can have elements of any type except of objects, and different elements of the same array may be of different types"
        ],
        "correctAnswer": 2,
        "verified": 1
    },
    {
        "question": "Is it a good practice to use the &lt;h1&gt; element whenever you need a large font?",
        "options": [
            "No, since the browser does not display more than one &lt;h1&gt; element on the same page",
            "Yes, since the resulting page will be responsive, indeed on every device the content of the &lt;h1&gt; element will have a bigger font",
            "Yes, since we will be sure that each browser will display the content of the &lt;h1&gt; element with a bigger font",
            "No, since by doing it we violate the semantic meaning associated to the &lt;h1&gt; element"
        ],
        "correctAnswer": 3,
        "verified": 1
    },
    {
        "question": "What is UTF-8?",
        "options": [
            "A control character for line printers",
            "An encoding of binary data over textual data",
            "A compact encoding of Unicode characters",
            "A subset of the extend ASCII character set"
        ],
        "correctAnswer": 2,
        "verified": 1
    },
    {
        "question": "Who did invent the Web?",
        "options": [
            "Ted Nelson",
            "Nicola Pellow",
            "Tim Berners-Lee",
            "Vannevar Bush"
        ],
        "correctAnswer": 2,
        "verified": 1
    },
    {
        "question": "What data type is most appropriate for portably representing a specific instant in time?",
        "options": [
            "TIME WITH TIMEZONE",
            "TIMESTAMP WITHOUT TIMEZONE",
            "TIMESTAMP WITH TIMEZONE",
            "TIME WITHOUT TIMEZONE"
        ],
        "correctAnswer": 2,
        "verified": 0
    },
    {
        "question": "What is a procedural markup language?",
        "options": [
            "It contains commands to format and layout the content",
            "It defines the type or class of the content to indicate its intended use",
            "It refers to entities external to the document",
            "It provides the means for extending the vocabulary of the language"
        ],
        "correctAnswer": 0,
        "verified": 1
    },
    {
        "question": "How do you specify the background color and opacity of a paragraph with CSS3?",
        "options": [
            "background-color: rgb(0,0,0); opacity: 0.5;",
            "background-color: rgba(0,0,0,0.5);",
            "background-color: rgb(0,0,0,0.5);",
            "background: rgb(0,0,0); opacity: 0.5;"
        ],
        "correctAnswer": [0, 1],
        "verified": 1
    },
    {
        "question": "What is an HTTP/2 message?",
        "options": [
            "It is an exchange of binary-encoded frames",
            "It is a bidirectional flow of byte within a connection which may carry one or messages",
            "It is a complete sequence of frames which map to a logical request or response",
            "It is the smallest unit of communication, containing also an header"
        ],
        "correctAnswer": 2,
        "verified": 1
    },
    {
        "question": "When programming with JavaScript you have to:",
        "options": [
            "Pay attention to lower and upper case letters since the language is case sensitive.",
            "Use the semicolon at the end of each statement.",
            "Declare the type of each variable.",
            "Perform garbage collection for memory management"
        ],
        "correctAnswer": 0,
        "verified": 1
    },
    {
        "question": "What is an identifier in the ER model?",
        "options": [
            "It is only one attribute of an entity whose value is unique for each instance of that entity",
            "It is a set of one or more attributes of an entity whose values are unique for each instance of that entity",
            "It is only one attribute of a relationship whose value is unique for each instance of that relationship",
            "It is a set of one or more attributes of a relationship whose values are unique for each instance of that relationship"
        ],
        "correctAnswer": 1,
        "verified": 1
    },
    {
        "question": "What is one of the goals of distributed applications?",
        "options": [
            "To increase the complexity of the application",
            "To hamper interoperability",
            "To distribute the computational load of the data, application, and presentation logic on different machines",
            "To decrease the complexity of the application"
        ],
        "correctAnswer": 2,
        "verified": 1
    },
    {
        "question": "What is a session/transient HTTP cookie?",
        "options": [
            "It is limited to encrypted transmissions",
            "It stores information which lasts also after the end of a session",
            "It belongs to a domain different from the one shown in the address bar",
            "It stores information which is deleted at the end of a session"
        ],
        "correctAnswer": 3,
        "verified": 1
    },
    {
        "question": "How do you group the following selectors: h1, h2, p?",
        "options": [
            "h1 h2 p ...",
            "h1, h2, p ...",
            "h1: h2: p ...",
            "h1; h2; p ..."
        ],
        "correctAnswer": 1,
        "verified": 1
    },
    {
        "question": "What is the purpose of the &lt;head&gt; element?",
        "options": [
            "It is contained in the body element and specifies general information about the page",
            "It can contain only the title of the page",
            "It contains the main heading of the page and the navigation bar",
            "It contains information about the page, as the title element and the meta elements"
        ],
        "correctAnswer": 3,
        "verified": 1
    },
    {
        "question": "Which of the following is a CSS id selector?",
        "options": [
            "#id ...",
            ".id ...",
            ":id ...",
            "id"
        ],
        "correctAnswer": 0,
        "verified": 1
    },
    {
        "question": "Suppose you have the following table <br>CREATE TABLE Example (<br> taskID INT,<br> description VARCHAR(64),<br> supertask INT,<br> PRIMARY KEY (taskID),<br> FOREIGN KEY (supertask) REFERENCES Example(taskID));<br> containing the following data<br>TaskID Description Supertask<br>10 Task 1011 Task 11 4512 Task 12 3713 Task 13 2929 Task 2937 Task 37 1045 Task 45 10101 Task 101 37194 Task 194 29 <br>and that you need to determine which tasks have more than one sub-task. Which statement is correct?",
        "options": [
            "SELECT supertask,<br> COUNT(*) AS subtasks<br> FROM Example<br> GROUP BY supertask<br> HAVING COUNT(*) > 1;",
            "SELECT supertask,<br> COUNT(*) AS subtasks<br> FROM Example<br> WHERE COUNT(*) > 1<br> GROUP BY supertask;",
            "SELECT supertask,<br> COUNT(*) AS subtasks<br> FROM Example<br> WHERE supertask IS NOT NULL AND COUNT(*) > 1 <br>GROUP BY supertask;",
            "SELECT supertask,<br> COUNT(*) AS subtasks<br> FROM Example<br> WHERE supertask IS NOT NULL<br> GROUP BY supertask <br>HAVING COUNT(*) > 1;"
        ],
        "correctAnswer": 3,
        "verified": 1
    },
    {
        "question": "Suppose you need to check that a laude is given only if the mark is 30. Which statement is correct?",
        "options": [
            "CREATE TABLE Example (<br> studentID INT,<br> courseID INT,<br> mark INT CHECK(mark >= 18 AND mark <= 30),<br> laude BOOLEAN,<br> PRIMARY KEY (studentID, courseID),<br> CHECK (mark = 30 OR NOT laude = TRUE) );",
            "CREATE TABLE Example (<br> studentID INT,<br> courseID INT,<br> mark INT CHECK(mark >= 18 AND mark <= 30),<br> laude BOOLEAN,<br> PRIMARY KEY (studentID, courseID),<br> CHECK (mark = 30 AND laude = TRUE) );",
            "CREATE TABLE Example (<br> studentID INT,<br> courseID INT,<br> mark INT CHECK(mark >= 18 AND mark <= 30),<br> laude BOOLEAN,<br> PRIMARY KEY (studentID, courseID),<br> CHECK (mark = 30 AND NOT laude = TRUE) );",
            "CREATE TABLE Example (<br> studentID INT,<br> courseID INT,<br> mark INT CHECK(mark >= 18 AND mark <= 30),<br> laude BOOLEAN,<br> PRIMARY KEY (studentID, courseID),<br> CHECK (mark = 30 OR laude = TRUE) );"
        ],
        "correctAnswer": 0,
        "verified": 0
    },
    {
        "question": "What is the semantic Web?",
        "options": [
            "It is a new type of Web applications where users can express themselves using the natural language semantics",
            "It is the Web of data where resources are connected by means of typed links",
            "It is the evolution of the Web where contents are more meaningful to human beings",
            "It is the evolution of the Web where the contents of an HTML page are clearly described"
        ],
        "correctAnswer": 1,
        "verified": 1
    },
    {
        "question": "What is a WebML non-contextual link?",
        "options": [
            "It is a link which does not transport information",
            "It is a link between two different units on the same page",
            "It is a link which transport information",
            "It is a link between two different pages"
        ],
        "correctAnswer": 1,
        "verified": 1
    },
    {
        "question": "What is the purpose of the JavaScript confirm() method?",
        "options": [
            "It displays a message, waits for the user to click an OK or Cancel button and returns a boolean value.",
            "It display a message to the user and write the corresponding console log.",
            "It displays a message, waits for the user to enter a string, and returns that string.",
            "It displays a message to the user and waits for the user to dismiss the dialog"
        ],
        "correctAnswer": 0,
        "verified": 1
    },
    {
        "question": "What is an HTTP/2 frame?",
        "options": [
            "It is a bidirectional flow of byte within a connection which may carry one or messages",
            "It is the smallest unit of communication, containing also an header",
            "It is a complete sequence of frames which map to a logical request or response",
            "It is an exchange of binary-encoded messages"
        ],
        "correctAnswer": 1,
        "verified": 1
    },
    {
        "question": "What is XML?",
        "options": [
            "It is an extension of HTML",
            "It is a markup language for representing and exchanging semi-structured information",
            "It is an implementation of WebML",
            "It is an extension of SGML"
        ],
        "correctAnswer": 1,
        "verified": 1
    },
    {
        "question": "JavaScript objects:",
        "options": [
            "Are static utility methods.",
            "Are a collection of values.",
            "Have only a fixed number of properties defined in advance.",
            "Are represented as associative arrays"
        ],
        "correctAnswer": 3,
        "verified": 1
    },
    {
        "question": "What are the disadvantages of a three-tiers architecture?",
        "options": [
            "Management of the terminals",
            "Scalability",
            "Difficulty of implementation",
            "Possibility to balance the load"
        ],
        "correctAnswer": 2,
        "verified": 1
    }
]
